{"715563231":{"speak":15,"pic":0,"biliLink":0,"repeat":0,"repeatBreak":0,"pohai":0,"sp":0,"mengEr":0,"time":0,"grass":0},"875388105":{"speak":1034,"pic":0,"biliLink":0,"repeat":0,"repeatBreak":0,"pohai":0,"sp":0,"mengEr":0,"time":0,"grass":12},"727529102":{"speak":1089,"pic":0,"biliLink":0,"repeat":0,"repeatBreak":0,"pohai":0,"sp":0,"mengEr":0,"time":0,"grass":18},"1070848429":{"speak":50,"pic":0,"biliLink":0,"repeat":0,"repeatBreak":0,"pohai":0,"sp":0,"mengEr":0,"time":0,"grass":0},"385292256":{"speak":8,"pic":0,"biliLink":0,"repeat":0,"repeatBreak":0,"pohai":0,"sp":0,"mengEr":0,"time":0,"grass":0},"1075494796":{"speak":2560,"pic":0,"biliLink":0,"repeat":0,"repeatBreak":0,"pohai":0,"sp":0,"mengEr":0,"time":0,"grass":78},"967841934":{"speak":302,"pic":0,"biliLink":0,"repeat":0,"repeatBreak":0,"pohai":0,"sp":0,"mengEr":0,"time":0,"grass":4},"1055451987":{"speak":266,"pic":0,"biliLink":0,"repeat":0,"repeatBreak":0,"pohai":0,"sp":0,"mengEr":0,"time":0,"grass":1},"202324718":{"speak":4970,"pic":0,"biliLink":0,"repeat":0,"repeatBreak":0,"pohai":0,"sp":0,"mengEr":0,"time":0,"grass":51},"243298910":{"speak":2309,"pic":0,"biliLink":0,"repeat":0,"repeatBreak":0,"pohai":0,"sp":0,"mengEr":0,"time":0,"grass":37},"617745343":{"speak":21519,"pic":0,"biliLink":0,"repeat":0,"repeatBreak":0,"pohai":0,"sp":0,"mengEr":0,"time":0,"grass":723},"1004984648":{"speak":2707,"pic":0,"biliLink":0,"repeat":0,"repeatBreak":0,"pohai":0,"sp":0,"mengEr":0,"time":0,"grass":88},"1047229554":{"speak":3443,"pic":0,"biliLink":0,"repeat":0,"repeatBreak":0,"pohai":0,"sp":0,"mengEr":0,"time":0,"grass":185},"959615179":{"speak":928,"pic":0,"biliLink":0,"repeat":0,"repeatBreak":0,"pohai":0,"sp":0,"mengEr":0,"time":0,"grass":78},"1037177816":{"speak":510,"pic":0,"biliLink":0,"repeat":0,"repeatBreak":0,"pohai":0,"sp":0,"mengEr":0,"time":0,"grass":2},"470753802":{"speak":1933,"pic":0,"biliLink":0,"repeat":0,"repeatBreak":0,"pohai":0,"sp":0,"mengEr":0,"time":0,"grass":14},"725891775":{"speak":4,"pic":0,"biliLink":0,"repeat":0,"repeatBreak":0,"pohai":0,"sp":0,"mengEr":0,"time":0,"grass":0},"1027953395":{"speak":14,"pic":0,"biliLink":0,"repeat":0,"repeatBreak":0,"pohai":0,"sp":0,"mengEr":0,"time":0,"grass":1},"1124883960":{"speak":17,"pic":0,"biliLink":0,"repeat":0,"repeatBreak":0,"pohai":0,"sp":0,"mengEr":0,"time":0,"grass":0},"1063213166":{"speak":12,"pic":0,"biliLink":0,"repeat":0,"repeatBreak":0,"pohai":0,"sp":0,"mengEr":0,"time":0,"grass":0},"793236161":{"speak":12083,"pic":0,"biliLink":0,"repeat":0,"repeatBreak":0,"pohai":0,"sp":0,"mengEr":0,"time":0,"grass":670},"732088034":{"speak":1839,"pic":0,"biliLink":0,"repeat":0,"repeatBreak":0,"pohai":0,"sp":0,"mengEr":0,"time":0,"grass":88},"859682537":{"speak":1173,"pic":0,"biliLink":0,"repeat":0,"repeatBreak":0,"pohai":0,"sp":0,"mengEr":0,"time":0,"grass":12},"807242547":{"speak":1,"pic":0,"biliLink":0,"repeat":0,"repeatBreak":0,"pohai":0,"sp":0,"mengEr":0,"time":0,"grass":1},"976915347":{"speak":165,"pic":0,"biliLink":0,"repeat":0,"repeatBreak":0,"pohai":0,"sp":0,"mengEr":0,"time":0,"grass":2},"739019465":{"speak":2,"pic":0,"biliLink":0,"repeat":0,"repeatBreak":0,"pohai":0,"sp":0,"mengEr":0,"time":0,"grass":0},"805058882":{"speak":1501,"pic":0,"biliLink":0,"repeat":0,"repeatBreak":0,"pohai":0,"sp":0,"mengEr":0,"time":0,"grass":95},"702276934":{"speak":1,"pic":0,"biliLink":0,"repeat":0,"repeatBreak":0,"pohai":0,"sp":0,"mengEr":0,"time":0,"grass":0},"859991644":{"speak":4292,"pic":0,"biliLink":0,"repeat":0,"repeatBreak":0,"pohai":0,"sp":0,"mengEr":0,"time":0,"grass":107},"1074383227":{"speak":1096,"pic":0,"biliLink":0,"repeat":0,"repeatBreak":0,"pohai":0,"sp":0,"mengEr":0,"time":0,"grass":48},"979028763":{"speak":971,"pic":0,"biliLink":0,"repeat":0,"repeatBreak":0,"pohai":0,"sp":0,"mengEr":0,"time":0,"grass":21},"317408300":{"speak":319,"pic":0,"biliLink":0,"repeat":0,"repeatBreak":0,"pohai":0,"sp":0,"mengEr":0,"time":0,"grass":4},"259614522":{"speak":46,"pic":0,"biliLink":0,"repeat":0,"repeatBreak":0,"pohai":0,"sp":0,"mengEr":0,"time":0,"grass":1},"106402733":{"speak":556,"pic":0,"biliLink":0,"repeat":0,"repeatBreak":0,"pohai":0,"sp":0,"mengEr":0,"time":0,"grass":3},"297456833":{"speak":34569,"pic":0,"biliLink":0,"repeat":0,"repeatBreak":0,"pohai":0,"sp":0,"mengEr":0,"time":0,"grass":448},"1107126986":{"speak":18,"pic":0,"biliLink":0,"repeat":0,"repeatBreak":0,"pohai":0,"sp":0,"mengEr":0,"time":0,"grass":0},"973510746":{"speak":15676,"pic":0,"biliLink":0,"repeat":0,"repeatBreak":0,"pohai":0,"sp":0,"mengEr":0,"time":0,"grass":447},"728439607":{"speak":3678,"pic":0,"biliLink":0,"repeat":0,"repeatBreak":0,"pohai":0,"sp":0,"mengEr":0,"time":0,"grass":56},"984951418":{"speak":9,"pic":0,"biliLink":0,"repeat":0,"repeatBreak":0,"pohai":0,"sp":0,"mengEr":0,"time":0,"grass":1},"366095737":{"speak":3647,"pic":0,"biliLink":0,"repeat":0,"repeatBreak":0,"pohai":0,"sp":0,"mengEr":0,"time":0,"grass":7},"726522724":{"speak":518,"pic":0,"biliLink":0,"repeat":0,"repeatBreak":0,"pohai":0,"sp":0,"mengEr":0,"time":0,"grass":29},"316669817":{"speak":2914,"pic":0,"biliLink":0,"repeat":0,"repeatBreak":0,"pohai":0,"sp":0,"mengEr":0,"time":0,"grass":79},"786215936":{"speak":23,"pic":0,"biliLink":0,"repeat":0,"repeatBreak":0,"pohai":0,"sp":0,"mengEr":0,"time":0,"grass":0},"692321831":{"speak":852,"pic":0,"biliLink":0,"repeat":0,"repeatBreak":0,"pohai":0,"sp":0,"mengEr":0,"time":0,"grass":26},"319067216":{"speak":19,"pic":0,"biliLink":0,"repeat":0,"repeatBreak":0,"pohai":0,"sp":0,"mengEr":0,"time":0,"grass":0},"859561731":{"speak":17,"pic":0,"biliLink":0,"repeat":0,"repeatBreak":0,"pohai":0,"sp":0,"mengEr":0,"time":0,"grass":2},"960010720":{"speak":2,"pic":0,"biliLink":0,"repeat":0,"repeatBreak":0,"pohai":0,"sp":0,"mengEr":0,"time":0,"grass":0},"109411658":{"speak":20743,"pic":0,"biliLink":0,"repeat":0,"repeatBreak":0,"pohai":0,"sp":0,"mengEr":0,"time":0,"grass":73},"901810148":{"speak":807,"pic":0,"biliLink":0,"repeat":0,"repeatBreak":0,"pohai":0,"sp":0,"mengEr":0,"time":0,"grass":9},"101344113":{"speak":4824,"pic":0,"biliLink":0,"repeat":0,"repeatBreak":0,"pohai":0,"sp":0,"mengEr":0,"time":0,"grass":16},"306639428":{"speak":97,"pic":0,"biliLink":0,"repeat":0,"repeatBreak":0,"pohai":0,"sp":0,"mengEr":0,"time":0,"grass":1},"764479958":{"speak":4899,"pic":0,"biliLink":0,"repeat":0,"repeatBreak":0,"pohai":0,"sp":0,"mengEr":0,"time":0,"grass":9},"431483450":{"speak":1996,"pic":0,"biliLink":0,"repeat":0,"repeatBreak":0,"pohai":0,"sp":0,"mengEr":0,"time":0,"grass":33},"424838564":{"speak":96,"pic":0,"biliLink":0,"repeat":0,"repeatBreak":0,"pohai":0,"sp":0,"mengEr":0,"time":0,"grass":0},"690571939":{"speak":1595,"pic":0,"biliLink":0,"repeat":0,"repeatBreak":0,"pohai":0,"sp":0,"mengEr":0,"time":0,"grass":53},"337495810":{"speak":2459,"pic":0,"biliLink":0,"repeat":0,"repeatBreak":0,"pohai":0,"sp":0,"mengEr":0,"time":0,"grass":49},"564453348":{"speak":37,"pic":0,"biliLink":0,"repeat":0,"repeatBreak":0,"pohai":0,"sp":0,"mengEr":0,"time":0,"grass":1},"943409150":{"speak":109,"pic":0,"biliLink":0,"repeat":0,"repeatBreak":0,"pohai":0,"sp":0,"mengEr":0,"time":0,"grass":1},"967855573":{"speak":2,"pic":0,"biliLink":0,"repeat":0,"repeatBreak":0,"pohai":0,"sp":0,"mengEr":0,"time":0,"grass":0},"660202799":{"speak":3009,"pic":0,"biliLink":0,"repeat":0,"repeatBreak":0,"pohai":0,"sp":0,"mengEr":0,"time":0,"grass":331},"568682935":{"speak":23,"pic":0,"biliLink":0,"repeat":0,"repeatBreak":0,"pohai":0,"sp":0,"mengEr":0,"time":0,"grass":0}}